BitlyOAuth2ProxySession/Session.py
BitlyOAuth2ProxySession/__init__.py
bitly_oauth2_proxy_session-0.1.5.dist-info/DESCRIPTION.rst
bitly_oauth2_proxy_session-0.1.5.dist-info/METADATA
bitly_oauth2_proxy_session-0.1.5.dist-info/RECORD
bitly_oauth2_proxy_session-0.1.5.dist-info/WHEEL
bitly_oauth2_proxy_session-0.1.5.dist-info/metadata.json
bitly_oauth2_proxy_session-0.1.5.dist-info/top_level.txt
