Metadata-Version: 2.0
Name: bitly-oauth2-proxy-session
Version: 0.1.5
Summary: LSST Data Management SQuaRE Bitly-Proxy Authenticated Sessions
Home-page: https://github.com/lsst-sqre/BitlyOAuth2ProxySession/
Author: Adam Thornton
Author-email: athornton@lsst.org
License: MIT
Keywords: lsst
Platform: UNKNOWN
Classifier: Development Status :: 4 - Beta
Classifier: Programming Language :: Python :: 2.7
Classifier: Programming Language :: Python :: 3.5
Classifier: License :: OSI Approved :: MIT License
Requires-Dist: requests (<3.0.0,>=2.13.0)
